SRToolkit/__init__.py
SRToolkit/dataset/__init__.py
SRToolkit/dataset/srbenchmark.py
SRToolkit/dataset/srdataset.py
SRToolkit/evaluation/__init__.py
SRToolkit/evaluation/parameter_estimator.py
SRToolkit/evaluation/sr_evaluator.py
SRToolkit/utils/__init__.py
SRToolkit/utils/expression_compiler.py
SRToolkit/utils/expression_generator.py
SRToolkit/utils/expression_simplifier.py
SRToolkit/utils/expression_tree.py
SRToolkit/utils/symbol_library.py
symbolic_regression_toolkit-1.3.3.dist-info/LICENSE
symbolic_regression_toolkit-1.3.3.dist-info/METADATA
symbolic_regression_toolkit-1.3.3.dist-info/WHEEL
symbolic_regression_toolkit-1.3.3.dist-info/top_level.txt
symbolic_regression_toolkit-1.3.3.dist-info/RECORD
