Metadata-Version: 2.1
Name: symbolic-regression-toolkit
Version: 1.3.3
Summary: Symbolic Regression/Equation Discovery Toolkit
Author-email: Sebastian Mežnar <smeznar@gmail.com>
License: GPL-3.0-only
Project-URL: Homepage, https://github.com/smeznar/SymbolicRegressionToolkit
Project-URL: Documentation, https://smeznar.github.io/SymbolicRegressionToolkit/
Keywords: symbolic regression,equation discovery,parameter estimation,machine learning
Classifier: Intended Audience :: Information Technology
Classifier: Intended Audience :: Science/Research
Classifier: License :: OSI Approved :: GNU General Public License v3 (GPLv3)
Classifier: Operating System :: OS Independent
Classifier: Programming Language :: Python :: 3
Classifier: Topic :: Scientific/Engineering
Classifier: Topic :: Scientific/Engineering :: Artificial Intelligence
Classifier: Topic :: Scientific/Engineering :: Mathematics
Requires-Python: >=3.7
License-File: LICENSE
Requires-Dist: numpy
Requires-Dist: scipy
Requires-Dist: sympy
Requires-Dist: nltk
